mlx_audio/__init__.py
mlx_audio/audio_io.py
mlx_audio/base.py
mlx_audio/convert.py
mlx_audio/dsp.py
mlx_audio/server.py
mlx_audio/utils.py
mlx_audio/version.py
mlx_audio/codec/__init__.py
mlx_audio/codec/models/__init__.py
mlx_audio/codec/models/bigvgan/__init__.py
mlx_audio/codec/models/bigvgan/activation.py
mlx_audio/codec/models/bigvgan/amp.py
mlx_audio/codec/models/bigvgan/bigvgan.py
mlx_audio/codec/models/bigvgan/conv.py
mlx_audio/codec/models/bigvgan/resample.py
mlx_audio/codec/models/dacvae/__init__.py
mlx_audio/codec/models/dacvae/codec.py
mlx_audio/codec/models/descript/__init__.py
mlx_audio/codec/models/descript/base.py
mlx_audio/codec/models/descript/dac.py
mlx_audio/codec/models/descript/nn/__init__.py
mlx_audio/codec/models/descript/nn/layers.py
mlx_audio/codec/models/descript/nn/quantize.py
mlx_audio/codec/models/encodec/__init__.py
mlx_audio/codec/models/encodec/encodec.py
mlx_audio/codec/models/mimi/__init__.py
mlx_audio/codec/models/mimi/mimi.py
mlx_audio/codec/models/mimi/modules/__init__.py
mlx_audio/codec/models/mimi/modules/conv.py
mlx_audio/codec/models/mimi/modules/quantization.py
mlx_audio/codec/models/mimi/modules/seanet.py
mlx_audio/codec/models/mimi/modules/transformer.py
mlx_audio/codec/models/s3/__init__.py
mlx_audio/codec/models/s3/model.py
mlx_audio/codec/models/s3/model_v2.py
mlx_audio/codec/models/s3/utils.py
mlx_audio/codec/models/snac/__init__.py
mlx_audio/codec/models/snac/attention.py
mlx_audio/codec/models/snac/layers.py
mlx_audio/codec/models/snac/snac.py
mlx_audio/codec/models/snac/vq.py
mlx_audio/codec/models/vocos/__init__.py
mlx_audio/codec/models/vocos/mel.py
mlx_audio/codec/models/vocos/vocos.py
mlx_audio/codec/tests/__init__.py
mlx_audio/codec/tests/test_bigvgan.py
mlx_audio/codec/tests/test_descript.py
mlx_audio/codec/tests/test_encodec.py
mlx_audio/codec/tests/test_mimi.py
mlx_audio/codec/tests/test_s3.py
mlx_audio/codec/tests/test_snac.py
mlx_audio/codec/tests/test_vocos.py
mlx_audio/sts/__init__.py
mlx_audio-0.3.1.dist-info/licenses/LICENSE
mlx_audio-0.3.1.dist-info/METADATA
mlx_audio-0.3.1.dist-info/WHEEL
mlx_audio-0.3.1.dist-info/entry_points.txt
mlx_audio-0.3.1.dist-info/top_level.txt
mlx_audio-0.3.1.dist-info/RECORD
