Metadata-Version: 2.4
Name: mlx-audio
Version: 0.3.1
Summary: MLX-Audio is a package for inference of text-to-speech (TTS) and speech-to-speech (STS) models locally on your Mac using MLX
Author-email: Prince Canuma <prince.gdt@gmail.com>
License-Expression: MIT
Project-URL: Homepage, https://github.com/Blaizzy/mlx-audio
Project-URL: Repository, https://github.com/Blaizzy/mlx-audio
Classifier: Programming Language :: Python :: 3
Classifier: Operating System :: OS Independent
Requires-Python: >=3.10
License-File: LICENSE
Requires-Dist: mlx>=0.25.2
Requires-Dist: numpy>=1.26.4
Requires-Dist: huggingface_hub>=0.27.0
Requires-Dist: transformers==5.0.0rc3
Requires-Dist: mlx-lm==0.30.5
Requires-Dist: tqdm>=4.67.1
Requires-Dist: sounddevice==0.5.3
Requires-Dist: miniaudio>=1.61
Requires-Dist: pyloudnorm>=0.2.0
Requires-Dist: numba>=0.60.0
Requires-Dist: librosa==0.11.0
Provides-Extra: stt
Requires-Dist: tiktoken>=0.9.0; extra == "stt"
Requires-Dist: mistral-common[audio]; extra == "stt"
Provides-Extra: tts
Requires-Dist: misaki>=0.9.4; extra == "tts"
Requires-Dist: num2words>=0.5.14; extra == "tts"
Requires-Dist: spacy>=3.8.4; extra == "tts"
Requires-Dist: phonemizer-fork>=3.3.2; extra == "tts"
Requires-Dist: espeakng-loader>=0.2.4; extra == "tts"
Requires-Dist: sentencepiece>=0.2.0; extra == "tts"
Provides-Extra: server
Requires-Dist: fastapi>=0.95.0; extra == "server"
Requires-Dist: uvicorn>=0.22.0; extra == "server"
Requires-Dist: python-multipart>=0.0.22; extra == "server"
Provides-Extra: sts
Requires-Dist: tiktoken>=0.9.0; extra == "sts"
Requires-Dist: mistral-common[audio]; extra == "sts"
Requires-Dist: misaki>=0.9.4; extra == "sts"
Requires-Dist: num2words>=0.5.14; extra == "sts"
Requires-Dist: spacy>=3.8.4; extra == "sts"
Requires-Dist: phonemizer-fork>=3.3.2; extra == "sts"
Requires-Dist: espeakng-loader>=0.2.4; extra == "sts"
Requires-Dist: sentencepiece>=0.2.0; extra == "sts"
Requires-Dist: webrtcvad>=2.0.10; extra == "sts"
Provides-Extra: all
Requires-Dist: tiktoken>=0.9.0; extra == "all"
Requires-Dist: mistral-common[audio]; extra == "all"
Requires-Dist: misaki>=0.9.4; extra == "all"
Requires-Dist: num2words>=0.5.14; extra == "all"
Requires-Dist: spacy>=3.8.4; extra == "all"
Requires-Dist: phonemizer-fork>=3.3.2; extra == "all"
Requires-Dist: espeakng-loader>=0.2.4; extra == "all"
Requires-Dist: sentencepiece>=0.2.0; extra == "all"
Requires-Dist: fastapi>=0.95.0; extra == "all"
Requires-Dist: uvicorn>=0.22.0; extra == "all"
Requires-Dist: webrtcvad>=2.0.10; extra == "all"
Provides-Extra: dev
Requires-Dist: pytest>=7.0.0; extra == "dev"
Requires-Dist: pytest-asyncio>=1.0.0; extra == "dev"
Dynamic: license-file
